simtools/__init__.py
simtools/utils.py
test/__init__.py
test/test_utils.py
particle_simtools-0.0.3.dist-info/LICENSE
particle_simtools-0.0.3.dist-info/METADATA
particle_simtools-0.0.3.dist-info/WHEEL
particle_simtools-0.0.3.dist-info/top_level.txt
particle_simtools-0.0.3.dist-info/RECORD
