Metadata-Version: 2.1
Name: particle-simtools
Version: 0.0.3
Summary: A collection of functions to help with simulating and running particle simulations.
Home-page: https://github.com/sciencectn/simtools
Author: Chris Taylor
Author-email: sciencectn@gmail.com
License: UNKNOWN
Platform: UNKNOWN
Requires-Dist: pyquaternion
